vyviz/__init__.py
vyviz/_server.py
vyviz/base/ace_editor.js
vyviz/base/actions.js
vyviz/base/colors.css
vyviz/base/favicon.ico
vyviz/base/framework.js
vyviz/base/graph.js
vyviz/base/graph_model.js
vyviz/base/log.js
vyviz/base/logs.css
vyviz/base/main.css
vyviz/base/main.html
vyviz/base/menuitems.js
vyviz/base/messages.js
vyviz/base/model.js
vyviz/base/typebuttons.js
vyviz/base/utilities.js
vyviz-0.0.12.dist-info/METADATA
vyviz-0.0.12.dist-info/WHEEL
vyviz-0.0.12.dist-info/entry_points.txt
vyviz-0.0.12.dist-info/top_level.txt
vyviz-0.0.12.dist-info/RECORD
