Metadata-Version: 2.1
Name: vyviz
Version: 0.0.12
Summary: Visualization tools for working with vy
Home-page: https://github.com/NateBu/vyviz
Author: Nate Bunderson
Author-email: nbunderson@gmail.com
License: MIT
Keywords: vy,vytools,vyviz
Classifier: Programming Language :: Python
Classifier: Development Status :: 2 - Pre-Alpha
Classifier: Intended Audience :: Developers
Classifier: License :: OSI Approved :: MIT License
Classifier: Operating System :: OS Independent
Classifier: Programming Language :: Python :: 3
Classifier: Topic :: Other/Nonlisted Topic
Requires-Python: >=3.7
Requires-Dist: sanic-cors (>=2.0.1)
Requires-Dist: vytools (>=0.4.6)
